gittools/__init__.py
gittools/gittools.py
gittools-0.6.0.dist-info/LICENSE
gittools-0.6.0.dist-info/METADATA
gittools-0.6.0.dist-info/WHEEL
gittools-0.6.0.dist-info/top_level.txt
gittools-0.6.0.dist-info/RECORD
