Metadata-Version: 2.1
Name: gittools
Version: 0.6.0
Summary: Tools to get git version information on files and python modules
Home-page: https://github.com/ovinc/gittools
Author: Olivier Vincent
Author-email: ovinc.py@gmail.com
License: BSD 3-Clause License
Keywords: git,python
Platform: UNKNOWN
Classifier: Programming Language :: Python :: 3
Classifier: Programming Language :: Python :: 3.6
Classifier: Programming Language :: Python :: 3.7
Classifier: Programming Language :: Python :: 3.8
Classifier: Programming Language :: Python :: 3.9
Classifier: License :: OSI Approved :: BSD License
Classifier: Operating System :: OS Independent
Requires-Python: >=3.6
Requires-Dist: gitpython
Requires-Dist: importlib-metadata
